{
  "generated_at": "2026-04-04T16:57:44.406838+00:00",
  "raw_data_dir": "C:\\Users\\kritu\\Desktop\\PROJECTS 6TH SEM\\Social-Media-Trends-Analyzer-main\\dataset\\raw_data",
  "preprocess_dir": "C:\\Users\\kritu\\Desktop\\PROJECTS 6TH SEM\\Social-Media-Trends-Analyzer-main\\dataset\\processed_data",
  "datasets": [
    {
      "name": "viral_social_media_trends",
      "title": "Viral Social Media Trends",
      "description": "Platform-level post performance with dates, regions, and engagement metrics.",
      "source_file": "Cleaned_Viral_Social_Media_Trends.csv",
      "processed_file": "viral_social_media_trends_processed.csv",
      "notebook_file": "01_viral_social_media_trends.ipynb",
      "raw_rows": 5000,
      "processed_rows": 5000,
      "column_count": 20,
      "columns": [
        "post_id",
        "post_date",
        "platform",
        "hashtag",
        "content_type",
        "region",
        "views",
        "likes",
        "shares",
        "comments",
        "engagement_level",
        "total_engagement",
        "engagement_rate",
        "year",
        "month",
        "year_month",
        "year_week",
        "source_dataset",
        "record_type",
        "primary_topic"
      ],
      "platforms": [
        "Instagram",
        "TikTok",
        "Twitter",
        "YouTube"
      ],
      "sentiments": [],
      "date_columns": [
        "post_date"
      ],
      "preview": [
        {
          "post_id": "Post_1",
          "post_date": "2022-01-13",
          "platform": "TikTok",
          "hashtag": "#challenge",
          "content_type": "Video",
          "region": "Uk",
          "views": "4163464",
          "likes": "339431",
          "shares": "53135",
          "comments": "19346",
          "engagement_level": "High",
          "total_engagement": "411912",
          "engagement_rate": "0.098935",
          "year": "2022",
          "month": "1",
          "year_month": "2022-01",
          "year_week": "2022-W02",
          "source_dataset": "viral_social_media_trends",
          "record_type": "post",
          "primary_topic": "#challenge"
        },
        {
          "post_id": "Post_2",
          "post_date": "2022-05-13",
          "platform": "Instagram",
          "hashtag": "#education",
          "content_type": "Shorts",
          "region": "India",
          "views": "4155940",
          "likes": "215240",
          "shares": "65860",
          "comments": "27239",
          "engagement_level": "Medium",
          "total_engagement": "308339",
          "engagement_rate": "0.074192",
          "year": "2022",
          "month": "5",
          "year_month": "2022-05",
          "year_week": "2022-W19",
          "source_dataset": "viral_social_media_trends",
          "record_type": "post",
          "primary_topic": "#education"
        },
        {
          "post_id": "Post_3",
          "post_date": "2022-01-07",
          "platform": "Twitter",
          "hashtag": "#challenge",
          "content_type": "Video",
          "region": "Brazil",
          "views": "3666211",
          "likes": "327143",
          "shares": "39423",
          "comments": "36223",
          "engagement_level": "Medium",
          "total_engagement": "402789",
          "engagement_rate": "0.109865",
          "year": "2022",
          "month": "1",
          "year_month": "2022-01",
          "year_week": "2022-W01",
          "source_dataset": "viral_social_media_trends",
          "record_type": "post",
          "primary_topic": "#challenge"
        }
      ]
    },
    {
      "name": "tweet_sentiment_selection",
      "title": "Tweet Sentiment Selection",
      "description": "Short-form tweet text with curated sentiment and selected text spans.",
      "source_file": "Tweets.csv",
      "processed_file": "tweet_sentiment_selection_processed.csv",
      "notebook_file": "03_tweet_sentiment_selection.ipynb",
      "raw_rows": 27481,
      "processed_rows": 27481,
      "column_count": 17,
      "columns": [
        "text_id",
        "text",
        "selected_text",
        "sentiment",
        "primary_topic",
        "text_length",
        "word_count",
        "hashtag_count",
        "mention_count",
        "link_count",
        "question_count",
        "exclamation_count",
        "selected_text_length",
        "selected_text_ratio",
        "platform",
        "record_type",
        "source_dataset"
      ],
      "platforms": [
        "Twitter"
      ],
      "sentiments": [
        "negative",
        "neutral",
        "positive"
      ],
      "date_columns": [],
      "preview": [
        {
          "text_id": "cb774db0d1",
          "text": "I`d have responded, if I were going",
          "selected_text": "I`d have responded, if I were going",
          "sentiment": "neutral",
          "primary_topic": "no_explicit_topic",
          "text_length": "35",
          "word_count": "7",
          "hashtag_count": "0",
          "mention_count": "0",
          "link_count": "0",
          "question_count": "0",
          "exclamation_count": "0",
          "selected_text_length": "35",
          "selected_text_ratio": "1.0",
          "platform": "Twitter",
          "record_type": "tweet",
          "source_dataset": "tweet_sentiment_selection"
        },
        {
          "text_id": "549e992a42",
          "text": "Sooo SAD I will miss you here in San Diego!!!",
          "selected_text": "Sooo SAD",
          "sentiment": "negative",
          "primary_topic": "no_explicit_topic",
          "text_length": "45",
          "word_count": "10",
          "hashtag_count": "0",
          "mention_count": "0",
          "link_count": "0",
          "question_count": "0",
          "exclamation_count": "3",
          "selected_text_length": "8",
          "selected_text_ratio": "0.177778",
          "platform": "Twitter",
          "record_type": "tweet",
          "source_dataset": "tweet_sentiment_selection"
        },
        {
          "text_id": "088c60f138",
          "text": "my boss is bullying me...",
          "selected_text": "bullying me",
          "sentiment": "negative",
          "primary_topic": "no_explicit_topic",
          "text_length": "25",
          "word_count": "5",
          "hashtag_count": "0",
          "mention_count": "0",
          "link_count": "0",
          "question_count": "0",
          "exclamation_count": "0",
          "selected_text_length": "11",
          "selected_text_ratio": "0.44",
          "platform": "Twitter",
          "record_type": "tweet",
          "source_dataset": "tweet_sentiment_selection"
        }
      ]
    },
    {
      "name": "twitter_train_binary_sentiment",
      "title": "Twitter Binary Sentiment Training Data",
      "description": "Large-scale binary sentiment dataset for broader text and mood coverage.",
      "source_file": "twitter_train.csv",
      "processed_file": "twitter_train_binary_sentiment_processed.csv",
      "notebook_file": "04_twitter_binary_sentiment.ipynb",
      "raw_rows": 1523975,
      "processed_rows": 1523975,
      "column_count": 14,
      "columns": [
        "record_id",
        "text",
        "sentiment",
        "primary_topic",
        "text_length",
        "word_count",
        "hashtag_count",
        "mention_count",
        "link_count",
        "question_count",
        "exclamation_count",
        "platform",
        "record_type",
        "source_dataset"
      ],
      "platforms": [
        "Twitter"
      ],
      "sentiments": [
        "negative",
        "positive"
      ],
      "date_columns": [],
      "preview": [
        {
          "record_id": "tw_train_00000001",
          "text": "awww that s a bummer you shoulda got david carr of third day to do it d",
          "sentiment": "negative",
          "primary_topic": "no_explicit_topic",
          "text_length": "71",
          "word_count": "17",
          "hashtag_count": "0",
          "mention_count": "0",
          "link_count": "0",
          "question_count": "0",
          "exclamation_count": "0",
          "platform": "Twitter",
          "record_type": "tweet",
          "source_dataset": "twitter_train_binary_sentiment"
        },
        {
          "record_id": "tw_train_00000002",
          "text": "is upset that he can t update his facebook by texting it and might cry as a result school today also blah",
          "sentiment": "negative",
          "primary_topic": "no_explicit_topic",
          "text_length": "105",
          "word_count": "22",
          "hashtag_count": "0",
          "mention_count": "0",
          "link_count": "0",
          "question_count": "0",
          "exclamation_count": "0",
          "platform": "Twitter",
          "record_type": "tweet",
          "source_dataset": "twitter_train_binary_sentiment"
        },
        {
          "record_id": "tw_train_00000003",
          "text": "i dived many times for the ball managed to save the rest go out of bounds",
          "sentiment": "negative",
          "primary_topic": "no_explicit_topic",
          "text_length": "73",
          "word_count": "16",
          "hashtag_count": "0",
          "mention_count": "0",
          "link_count": "0",
          "question_count": "0",
          "exclamation_count": "0",
          "platform": "Twitter",
          "record_type": "tweet",
          "source_dataset": "twitter_train_binary_sentiment"
        }
      ]
    },
    {
      "name": "youtube_comments_sentiment",
      "title": "YouTube Comments Sentiment",
      "description": "Comment-level audience reactions and sentiment from YouTube discussions.",
      "source_file": "YoutubeCommentsDataSet.csv",
      "processed_file": "youtube_comments_sentiment_processed.csv",
      "notebook_file": "05_youtube_comments_sentiment.ipynb",
      "raw_rows": 18408,
      "processed_rows": 18408,
      "column_count": 14,
      "columns": [
        "record_id",
        "comment",
        "sentiment",
        "primary_topic",
        "text_length",
        "word_count",
        "hashtag_count",
        "mention_count",
        "link_count",
        "question_count",
        "exclamation_count",
        "platform",
        "record_type",
        "source_dataset"
      ],
      "platforms": [
        "YouTube"
      ],
      "sentiments": [
        "negative",
        "neutral",
        "positive"
      ],
      "date_columns": [],
      "preview": [
        {
          "record_id": "yt_comment_00000001",
          "comment": "lets not forget that apple pay in 2014 required a brand new iphone in order to use it a significant portion of apples user base wasnt able to use it even if they wanted to as each successive iphone incorporated the technology and older iphones were replaced the number of people who could use the technology increased",
          "sentiment": "neutral",
          "primary_topic": "no_explicit_topic",
          "text_length": "317",
          "word_count": "57",
          "hashtag_count": "0",
          "mention_count": "0",
          "link_count": "0",
          "question_count": "0",
          "exclamation_count": "0",
          "platform": "YouTube",
          "record_type": "comment",
          "source_dataset": "youtube_comments_sentiment"
        },
        {
          "record_id": "yt_comment_00000002",
          "comment": "here in nz 50 of retailers don\u2019t even have contactless credit card machines like paywave which support apple pay they don\u2019t like the high fees that come with these",
          "sentiment": "negative",
          "primary_topic": "no_explicit_topic",
          "text_length": "163",
          "word_count": "29",
          "hashtag_count": "0",
          "mention_count": "0",
          "link_count": "0",
          "question_count": "0",
          "exclamation_count": "0",
          "platform": "YouTube",
          "record_type": "comment",
          "source_dataset": "youtube_comments_sentiment"
        },
        {
          "record_id": "yt_comment_00000003",
          "comment": "i will forever acknowledge this channel with the help of your lessons and ideas explanations now its quite helpful while youll just sit at your comfort and monitor your account growth",
          "sentiment": "positive",
          "primary_topic": "no_explicit_topic",
          "text_length": "183",
          "word_count": "31",
          "hashtag_count": "0",
          "mention_count": "0",
          "link_count": "0",
          "question_count": "0",
          "exclamation_count": "0",
          "platform": "YouTube",
          "record_type": "comment",
          "source_dataset": "youtube_comments_sentiment"
        }
      ]
    },
    {
      "name": "youtube_trending_united_states",
      "title": "United States YouTube Trending Videos",
      "description": "Regional YouTube trending-video behavior for United States with views, likes, comments, and trend lag.",
      "source_file": "USvideos.csv",
      "processed_file": "youtube_trending_united_states_processed.csv",
      "notebook_file": "06_youtube_trending_united_states.ipynb",
      "raw_rows": 40949,
      "processed_rows": 40949,
      "column_count": 29,
      "columns": [
        "video_id",
        "title",
        "publish_time",
        "trending_date",
        "channel_title",
        "category_id",
        "tags",
        "primary_topic",
        "tag_count",
        "views",
        "likes",
        "dislikes",
        "comments",
        "total_engagement",
        "engagement_rate",
        "trend_lag_days",
        "comments_disabled",
        "ratings_disabled",
        "title_word_count",
        "description_length",
        "description_preview",
        "platform",
        "region",
        "source_dataset",
        "record_type",
        "year",
        "month",
        "year_month",
        "year_week"
      ],
      "platforms": [
        "YouTube"
      ],
      "sentiments": [],
      "date_columns": [
        "trending_date"
      ],
      "preview": [
        {
          "video_id": "2kyS6SvSYSE",
          "title": "WE WANT TO TALK ABOUT OUR MARRIAGE",
          "publish_time": "2017-11-13 17:13:01",
          "trending_date": "2017-11-14",
          "channel_title": "CaseyNeistat",
          "category_id": "22",
          "tags": "SHANtell martin",
          "primary_topic": "shantell martin",
          "tag_count": "1",
          "views": "748374",
          "likes": "57527",
          "dislikes": "2966",
          "comments": "15954",
          "total_engagement": "73481",
          "engagement_rate": "0.098188",
          "trend_lag_days": "0",
          "comments_disabled": "False",
          "ratings_disabled": "False",
          "title_word_count": "7",
          "description_length": "1404",
          "description_preview": "SHANTELL'S CHANNEL - https://www.youtube.com/shantellmartin\\nCANDICE - https://www.lovebilly.com\\n\\nfilmed this video in 4k on this -- http://amzn.to/2sTDnRZ\\nwith this lens -- http://amzn.to/2rUJOmD\\nbig drone - http://tinyurl.com/h4ft3oy\\nOTHER GEAR --- http://amzn.to/2o3GLX5\\n",
          "platform": "YouTube",
          "region": "United States",
          "source_dataset": "youtube_trending_united_states",
          "record_type": "video",
          "year": "2017",
          "month": "11",
          "year_month": "2017-11",
          "year_week": "2017-W46"
        },
        {
          "video_id": "1ZAPwfrtAFY",
          "title": "The Trump Presidency: Last Week Tonight with John Oliver (HBO)",
          "publish_time": "2017-11-13 07:30:00",
          "trending_date": "2017-11-14",
          "channel_title": "LastWeekTonight",
          "category_id": "24",
          "tags": "last week tonight trump presidency|\"last week tonight donald trump\"|\"john oliver trump\"|\"donald trump\"",
          "primary_topic": "last week tonight trump presidency",
          "tag_count": "4",
          "views": "2418783",
          "likes": "97185",
          "dislikes": "6146",
          "comments": "12703",
          "total_engagement": "109888",
          "engagement_rate": "0.045431",
          "trend_lag_days": "0",
          "comments_disabled": "False",
          "ratings_disabled": "False",
          "title_word_count": "10",
          "description_length": "630",
          "description_preview": "One year after the presidential election, John Oliver discusses what we've learned so far and enlists our catheter cowboy to teach Donald Trump what he hasn't.\\n\\nConnect with Last Week Tonight online...\\n\\nSubscribe to the Last Week Tonight YouTube channel for more almost news a",
          "platform": "YouTube",
          "region": "United States",
          "source_dataset": "youtube_trending_united_states",
          "record_type": "video",
          "year": "2017",
          "month": "11",
          "year_month": "2017-11",
          "year_week": "2017-W46"
        },
        {
          "video_id": "5qpjK5DgCt4",
          "title": "Racist Superman | Rudy Mancuso, King Bach & Lele Pons",
          "publish_time": "2017-11-12 19:05:24",
          "trending_date": "2017-11-14",
          "channel_title": "Rudy Mancuso",
          "category_id": "23",
          "tags": "racist superman|\"rudy\"|\"mancuso\"|\"king\"|\"bach\"|\"racist\"|\"superman\"|\"love\"|\"rudy mancuso poo bear black white official music video\"|\"iphone x by pineapple\"|\"lelepons\"|\"hannahstocking\"|\"rudymancuso\"|\"inanna\"|\"anwar\"|\"sarkis\"|\"shots\"|\"shotsstudios\"|\"alesso\"|\"anitta\"|\"brazil\"|\"Getting My Driver's License | Lele Pons\"",
          "primary_topic": "racist superman",
          "tag_count": "23",
          "views": "3191434",
          "likes": "146033",
          "dislikes": "5339",
          "comments": "8181",
          "total_engagement": "154214",
          "engagement_rate": "0.048321",
          "trend_lag_days": "1",
          "comments_disabled": "False",
          "ratings_disabled": "False",
          "title_word_count": "10",
          "description_length": "1177",
          "description_preview": "WATCH MY PREVIOUS VIDEO \u25b6 \\n\\nSUBSCRIBE \u25ba https://www.youtube.com/channel/UC5jkXpfnBhlDjqh0ir5FsIQ?sub_confirmation=1\\n\\nTHANKS FOR WATCHING! LIKE & SUBSCRIBE FOR MORE VIDEOS!\\n-----------------------------------------------------------\\nFIND ME ON: \\nInstagram | http://instagram",
          "platform": "YouTube",
          "region": "United States",
          "source_dataset": "youtube_trending_united_states",
          "record_type": "video",
          "year": "2017",
          "month": "11",
          "year_month": "2017-11",
          "year_week": "2017-W46"
        }
      ]
    },
    {
      "name": "youtube_trending_united_kingdom",
      "title": "United Kingdom YouTube Trending Videos",
      "description": "Regional YouTube trending-video behavior for United Kingdom with views, likes, comments, and trend lag.",
      "source_file": "GBvideos.csv",
      "processed_file": "youtube_trending_united_kingdom_processed.csv",
      "notebook_file": "07_youtube_trending_united_kingdom.ipynb",
      "raw_rows": 38916,
      "processed_rows": 38916,
      "column_count": 29,
      "columns": [
        "video_id",
        "title",
        "publish_time",
        "trending_date",
        "channel_title",
        "category_id",
        "tags",
        "primary_topic",
        "tag_count",
        "views",
        "likes",
        "dislikes",
        "comments",
        "total_engagement",
        "engagement_rate",
        "trend_lag_days",
        "comments_disabled",
        "ratings_disabled",
        "title_word_count",
        "description_length",
        "description_preview",
        "platform",
        "region",
        "source_dataset",
        "record_type",
        "year",
        "month",
        "year_month",
        "year_week"
      ],
      "platforms": [
        "YouTube"
      ],
      "sentiments": [],
      "date_columns": [
        "trending_date"
      ],
      "preview": [
        {
          "video_id": "Jw1Y-zhQURU",
          "title": "John Lewis Christmas Ad 2017 - #MozTheMonster",
          "publish_time": "2017-11-10 07:38:29",
          "trending_date": "2017-11-14",
          "channel_title": "John Lewis",
          "category_id": "26",
          "tags": "christmas|\"john lewis christmas\"|\"john lewis\"|\"christmas ad\"|\"mozthemonster\"|\"christmas 2017\"|\"christmas ad 2017\"|\"john lewis christmas advert\"|\"moz\"",
          "primary_topic": "christmas",
          "tag_count": "9",
          "views": "7224515",
          "likes": "55681",
          "dislikes": "10247",
          "comments": "9479",
          "total_engagement": "65160",
          "engagement_rate": "0.009019",
          "trend_lag_days": "3",
          "comments_disabled": "False",
          "ratings_disabled": "False",
          "title_word_count": "7",
          "description_length": "821",
          "description_preview": "Click here to continue the story and make your own monster:\\nhttp://bit.ly/2mboXgj\\n\\nJoe befriends a noisy Monster under his bed but the two have so much fun together that he can't get to sleep, leaving him tired by day. For Christmas Joe receives a gift to help him finally get ",
          "platform": "YouTube",
          "region": "United Kingdom",
          "source_dataset": "youtube_trending_united_kingdom",
          "record_type": "video",
          "year": "2017",
          "month": "11",
          "year_month": "2017-11",
          "year_week": "2017-W46"
        },
        {
          "video_id": "3s1rvMFUweQ",
          "title": "Taylor Swift: \u2026Ready for It? (Live) - SNL",
          "publish_time": "2017-11-12 06:24:44",
          "trending_date": "2017-11-14",
          "channel_title": "Saturday Night Live",
          "category_id": "24",
          "tags": "SNL|\"Saturday Night Live\"|\"SNL Season 43\"|\"Episode 1730\"|\"Tiffany Haddish\"|\"Taylor Swift\"|\"Taylor Swift Ready for It\"|\"s43\"|\"s43e5\"|\"episode 5\"|\"live\"|\"new york\"|\"comedy\"|\"sketch\"|\"funny\"|\"hilarious\"|\"late night\"|\"host\"|\"music\"|\"guest\"|\"laugh\"|\"impersonation\"|\"actor\"|\"improv\"|\"musician\"|\"comedian\"|\"actress\"|\"If Loving You Is Wrong\"|\"Oprah Winfrey\"|\"OWN\"|\"Girls Trip\"|\"The Carmichael Show\"|\"Keanu\"|\"Reputation\"|\"Look What You Made Me Do\"|\"ready for it?\"",
          "primary_topic": "snl",
          "tag_count": "36",
          "views": "1053632",
          "likes": "25561",
          "dislikes": "2294",
          "comments": "2757",
          "total_engagement": "28318",
          "engagement_rate": "0.026877",
          "trend_lag_days": "1",
          "comments_disabled": "False",
          "ratings_disabled": "False",
          "title_word_count": "8",
          "description_length": "417",
          "description_preview": "Musical guest Taylor Swift performs \u2026Ready for It? on Saturday Night Live.\\n\\n#SNL #SNL43\\n\\nGet more SNL: http://www.nbc.com/saturday-night-live\\nFull Episodes: http://www.nbc.com/saturday-night-liv...\\n\\nLike SNL: https://www.facebook.com/snl\\nFollow SNL: https://twitter.com/nb",
          "platform": "YouTube",
          "region": "United Kingdom",
          "source_dataset": "youtube_trending_united_kingdom",
          "record_type": "video",
          "year": "2017",
          "month": "11",
          "year_month": "2017-11",
          "year_week": "2017-W46"
        },
        {
          "video_id": "n1WpP7iowLc",
          "title": "Eminem - Walk On Water (Audio) ft. Beyonc\u00e9",
          "publish_time": "2017-11-10 17:00:03",
          "trending_date": "2017-11-14",
          "channel_title": "EminemVEVO",
          "category_id": "10",
          "tags": "Eminem|\"Walk\"|\"On\"|\"Water\"|\"Aftermath/Shady/Interscope\"|\"Rap\"",
          "primary_topic": "eminem",
          "tag_count": "6",
          "views": "17158579",
          "likes": "787420",
          "dislikes": "43420",
          "comments": "125882",
          "total_engagement": "913302",
          "engagement_rate": "0.053227",
          "trend_lag_days": "3",
          "comments_disabled": "False",
          "ratings_disabled": "False",
          "title_word_count": "8",
          "description_length": "594",
          "description_preview": "Eminem's new track Walk on Water ft. Beyonc\u00e9 is available everywhere: http://shady.sr/WOWEminem \\nPlaylist Best of Eminem: https://goo.gl/AquNpo\\nSubscribe for more: https://goo.gl/DxCrDV\\n\\nFor more visit: \\nhttp://eminem.com\\nhttp://facebook.com/eminem\\nhttp://twitter.com/emine",
          "platform": "YouTube",
          "region": "United Kingdom",
          "source_dataset": "youtube_trending_united_kingdom",
          "record_type": "video",
          "year": "2017",
          "month": "11",
          "year_month": "2017-11",
          "year_week": "2017-W46"
        }
      ]
    },
    {
      "name": "youtube_trending_canada",
      "title": "Canada YouTube Trending Videos",
      "description": "Regional YouTube trending-video behavior for Canada with views, likes, comments, and trend lag.",
      "source_file": "CAvideos.csv",
      "processed_file": "youtube_trending_canada_processed.csv",
      "notebook_file": "08_youtube_trending_canada.ipynb",
      "raw_rows": 40881,
      "processed_rows": 40881,
      "column_count": 29,
      "columns": [
        "video_id",
        "title",
        "publish_time",
        "trending_date",
        "channel_title",
        "category_id",
        "tags",
        "primary_topic",
        "tag_count",
        "views",
        "likes",
        "dislikes",
        "comments",
        "total_engagement",
        "engagement_rate",
        "trend_lag_days",
        "comments_disabled",
        "ratings_disabled",
        "title_word_count",
        "description_length",
        "description_preview",
        "platform",
        "region",
        "source_dataset",
        "record_type",
        "year",
        "month",
        "year_month",
        "year_week"
      ],
      "platforms": [
        "YouTube"
      ],
      "sentiments": [],
      "date_columns": [
        "trending_date"
      ],
      "preview": [
        {
          "video_id": "n1WpP7iowLc",
          "title": "Eminem - Walk On Water (Audio) ft. Beyonc\u00e9",
          "publish_time": "2017-11-10 17:00:03",
          "trending_date": "2017-11-14",
          "channel_title": "EminemVEVO",
          "category_id": "10",
          "tags": "Eminem|\"Walk\"|\"On\"|\"Water\"|\"Aftermath/Shady/Interscope\"|\"Rap\"",
          "primary_topic": "eminem",
          "tag_count": "6",
          "views": "17158579",
          "likes": "787425",
          "dislikes": "43420",
          "comments": "125882",
          "total_engagement": "913307",
          "engagement_rate": "0.053227",
          "trend_lag_days": "3",
          "comments_disabled": "False",
          "ratings_disabled": "False",
          "title_word_count": "8",
          "description_length": "594",
          "description_preview": "Eminem's new track Walk on Water ft. Beyonc\u00e9 is available everywhere: http://shady.sr/WOWEminem \\nPlaylist Best of Eminem: https://goo.gl/AquNpo\\nSubscribe for more: https://goo.gl/DxCrDV\\n\\nFor more visit: \\nhttp://eminem.com\\nhttp://facebook.com/eminem\\nhttp://twitter.com/emine",
          "platform": "YouTube",
          "region": "Canada",
          "source_dataset": "youtube_trending_canada",
          "record_type": "video",
          "year": "2017",
          "month": "11",
          "year_month": "2017-11",
          "year_week": "2017-W46"
        },
        {
          "video_id": "0dBIkQ4Mz1M",
          "title": "PLUSH - Bad Unboxing Fan Mail",
          "publish_time": "2017-11-13 17:00:00",
          "trending_date": "2017-11-14",
          "channel_title": "iDubbbzTV",
          "category_id": "23",
          "tags": "plush|\"bad unboxing\"|\"unboxing\"|\"fan mail\"|\"idubbbztv\"|\"idubbbztv2\"|\"things\"|\"best\"|\"packages\"|\"plushies\"|\"chontent chop\"",
          "primary_topic": "plush",
          "tag_count": "11",
          "views": "1014651",
          "likes": "127794",
          "dislikes": "1688",
          "comments": "13030",
          "total_engagement": "140824",
          "engagement_rate": "0.138791",
          "trend_lag_days": "0",
          "comments_disabled": "False",
          "ratings_disabled": "False",
          "title_word_count": "6",
          "description_length": "704",
          "description_preview": "STill got a lot of packages. Probably will last for another year. On a side note, more 2nd channel vids soon. editing with premiere from now on, gon' be a tedious transition, but i think it's for the best. \\n\\n__\\n\\nSUBSCRIBE \u25ba http://www.youtube.com/subscription_center?add_user=",
          "platform": "YouTube",
          "region": "Canada",
          "source_dataset": "youtube_trending_canada",
          "record_type": "video",
          "year": "2017",
          "month": "11",
          "year_month": "2017-11",
          "year_week": "2017-W46"
        },
        {
          "video_id": "5qpjK5DgCt4",
          "title": "Racist Superman | Rudy Mancuso, King Bach & Lele Pons",
          "publish_time": "2017-11-12 19:05:24",
          "trending_date": "2017-11-14",
          "channel_title": "Rudy Mancuso",
          "category_id": "23",
          "tags": "racist superman|\"rudy\"|\"mancuso\"|\"king\"|\"bach\"|\"racist\"|\"superman\"|\"love\"|\"rudy mancuso poo bear black white official music video\"|\"iphone x by pineapple\"|\"lelepons\"|\"hannahstocking\"|\"rudymancuso\"|\"inanna\"|\"anwar\"|\"sarkis\"|\"shots\"|\"shotsstudios\"|\"alesso\"|\"anitta\"|\"brazil\"|\"Getting My Driver's License | Lele Pons\"",
          "primary_topic": "racist superman",
          "tag_count": "23",
          "views": "3191434",
          "likes": "146035",
          "dislikes": "5339",
          "comments": "8181",
          "total_engagement": "154216",
          "engagement_rate": "0.048322",
          "trend_lag_days": "1",
          "comments_disabled": "False",
          "ratings_disabled": "False",
          "title_word_count": "10",
          "description_length": "1177",
          "description_preview": "WATCH MY PREVIOUS VIDEO \u25b6 \\n\\nSUBSCRIBE \u25ba https://www.youtube.com/channel/UC5jkXpfnBhlDjqh0ir5FsIQ?sub_confirmation=1\\n\\nTHANKS FOR WATCHING! LIKE & SUBSCRIBE FOR MORE VIDEOS!\\n-----------------------------------------------------------\\nFIND ME ON: \\nInstagram | http://instagram",
          "platform": "YouTube",
          "region": "Canada",
          "source_dataset": "youtube_trending_canada",
          "record_type": "video",
          "year": "2017",
          "month": "11",
          "year_month": "2017-11",
          "year_week": "2017-W46"
        }
      ]
    },
    {
      "name": "youtube_trending_germany",
      "title": "Germany YouTube Trending Videos",
      "description": "Regional YouTube trending-video behavior for Germany with views, likes, comments, and trend lag.",
      "source_file": "DEvideos.csv",
      "processed_file": "youtube_trending_germany_processed.csv",
      "notebook_file": "09_youtube_trending_germany.ipynb",
      "raw_rows": 40840,
      "processed_rows": 40840,
      "column_count": 29,
      "columns": [
        "video_id",
        "title",
        "publish_time",
        "trending_date",
        "channel_title",
        "category_id",
        "tags",
        "primary_topic",
        "tag_count",
        "views",
        "likes",
        "dislikes",
        "comments",
        "total_engagement",
        "engagement_rate",
        "trend_lag_days",
        "comments_disabled",
        "ratings_disabled",
        "title_word_count",
        "description_length",
        "description_preview",
        "platform",
        "region",
        "source_dataset",
        "record_type",
        "year",
        "month",
        "year_month",
        "year_week"
      ],
      "platforms": [
        "YouTube"
      ],
      "sentiments": [],
      "date_columns": [
        "trending_date"
      ],
      "preview": [
        {
          "video_id": "LgVi6y5QIjM",
          "title": "Sing zu Ende! | Gesangseinlagen vom Feinsten | inscope21",
          "publish_time": "2017-11-13 17:08:49",
          "trending_date": "2017-11-14",
          "channel_title": "inscope21",
          "category_id": "24",
          "tags": "inscope21|\"sing zu ende\"|\"gesangseinlagen\"|\"gesang\"|\"gesungen\"|\"songs nachsingen\"|\"nachsingen\"|\"songs covern\"|\"carpool karaoke\"|\"witziger gesang\"|\"rap\"|\"rap cover\"|\"rap zu ende\"|\"raps nachstellen\"|\"nachrappen\"|\"nach rappen\"",
          "primary_topic": "inscope21",
          "tag_count": "16",
          "views": "252786",
          "likes": "35885",
          "dislikes": "230",
          "comments": "1539",
          "total_engagement": "37424",
          "engagement_rate": "0.148046",
          "trend_lag_days": "0",
          "comments_disabled": "False",
          "ratings_disabled": "False",
          "title_word_count": "9",
          "description_length": "636",
          "description_preview": "Heute gibt es mal wieder ein neues Format... wenn euch das Ganze gef\u00e4llt lasst 1,5 Daumen nach oben da, dann bringen wir es nie wieder. Es wird gerappt gesungen und nichts gewusst, optimales Setup also. Kommentiert welche Songs ihr n\u00e4chstes Mal dabei haben wollt.\\n\\n\u25baMerch!: http",
          "platform": "YouTube",
          "region": "Germany",
          "source_dataset": "youtube_trending_germany",
          "record_type": "video",
          "year": "2017",
          "month": "11",
          "year_month": "2017-11",
          "year_week": "2017-W46"
        },
        {
          "video_id": "Bayt7uQith4",
          "title": "Kinder ferngesteuert im Kiosk! Erwachsene abzocken - LUKE! Die Woche und ich | SAT.1",
          "publish_time": "2017-11-12 22:30:01",
          "trending_date": "2017-11-14",
          "channel_title": "LUKE! Die Woche und ich",
          "category_id": "23",
          "tags": "Kinder|\"ferngesteuert\"|\"Kinder ferngesteuert\"|\"luke mockridge kinder\"|\"luke die woche und ich kinder\"|\"Prank\"|\"verarschen\"|\"Kiosk\"|\"Funkger\u00e4t\"|\"Falschgeld\"|\"Verk\u00e4ufer\"|\"Luke Mockridge\"|\"Luke Die Woche und ich\"|\"versteckte Kamera\"|\"Show\"|\"Sat.1\"|\"LDWUI\"|\"Comedy\"|\"Kioskverk\u00e4ufer\"|\"kinder prank\"|\"luke robin\"|\"Erwachsene abzocken\"|\"kunden verarschen\"|\"kunden prank\"|\"kasse prank\"|\"versteckte Kamera luke\"|\"luke kinder\"",
          "primary_topic": "kinder",
          "tag_count": "27",
          "views": "797196",
          "likes": "53576",
          "dislikes": "302",
          "comments": "1278",
          "total_engagement": "54854",
          "engagement_rate": "0.068809",
          "trend_lag_days": "1",
          "comments_disabled": "False",
          "ratings_disabled": "False",
          "title_word_count": "14",
          "description_length": "725",
          "description_preview": "Kinder ferngesteuert! Kinder lassen sich sooo leicht beeinflussen. So wie Robin, der sich von Luke als Kioskverk\u00e4ufer steuern l\u00e4sst. Die Kundern sind leicht irritiert. \\n\\n\u25baAbonniert den Kanal und verpasst kein \u201eLUKE \u2013 Die Woche und ich\u201c-Video!\\nhttps://www.youtube.com/channel/UC",
          "platform": "YouTube",
          "region": "Germany",
          "source_dataset": "youtube_trending_germany",
          "record_type": "video",
          "year": "2017",
          "month": "11",
          "year_month": "2017-11",
          "year_week": "2017-W46"
        },
        {
          "video_id": "1ZAPwfrtAFY",
          "title": "The Trump Presidency: Last Week Tonight with John Oliver (HBO)",
          "publish_time": "2017-11-13 07:30:00",
          "trending_date": "2017-11-14",
          "channel_title": "LastWeekTonight",
          "category_id": "24",
          "tags": "last week tonight trump presidency|\"last week tonight donald trump\"|\"john oliver trump\"|\"donald trump\"",
          "primary_topic": "last week tonight trump presidency",
          "tag_count": "4",
          "views": "2418783",
          "likes": "97190",
          "dislikes": "6146",
          "comments": "12703",
          "total_engagement": "109893",
          "engagement_rate": "0.045433",
          "trend_lag_days": "0",
          "comments_disabled": "False",
          "ratings_disabled": "False",
          "title_word_count": "10",
          "description_length": "630",
          "description_preview": "One year after the presidential election, John Oliver discusses what we've learned so far and enlists our catheter cowboy to teach Donald Trump what he hasn't.\\n\\nConnect with Last Week Tonight online...\\n\\nSubscribe to the Last Week Tonight YouTube channel for more almost news a",
          "platform": "YouTube",
          "region": "Germany",
          "source_dataset": "youtube_trending_germany",
          "record_type": "video",
          "year": "2017",
          "month": "11",
          "year_month": "2017-11",
          "year_week": "2017-W46"
        }
      ]
    },
    {
      "name": "youtube_trending_france",
      "title": "France YouTube Trending Videos",
      "description": "Regional YouTube trending-video behavior for France with views, likes, comments, and trend lag.",
      "source_file": "FRvideos.csv",
      "processed_file": "youtube_trending_france_processed.csv",
      "notebook_file": "10_youtube_trending_france.ipynb",
      "raw_rows": 40724,
      "processed_rows": 40724,
      "column_count": 29,
      "columns": [
        "video_id",
        "title",
        "publish_time",
        "trending_date",
        "channel_title",
        "category_id",
        "tags",
        "primary_topic",
        "tag_count",
        "views",
        "likes",
        "dislikes",
        "comments",
        "total_engagement",
        "engagement_rate",
        "trend_lag_days",
        "comments_disabled",
        "ratings_disabled",
        "title_word_count",
        "description_length",
        "description_preview",
        "platform",
        "region",
        "source_dataset",
        "record_type",
        "year",
        "month",
        "year_month",
        "year_week"
      ],
      "platforms": [
        "YouTube"
      ],
      "sentiments": [],
      "date_columns": [
        "trending_date"
      ],
      "preview": [
        {
          "video_id": "Ro6eob0LrCY",
          "title": "Malika LePen : Femme de Gauche - Trailer",
          "publish_time": "2017-11-13 17:32:55",
          "trending_date": "2017-11-14",
          "channel_title": "Le Raptor Dissident",
          "category_id": "24",
          "tags": "Raptor\"|\"Dissident\"|\"Expliquez\"|\"moi\"|\"cette\"|\"merde",
          "primary_topic": "raptor\"",
          "tag_count": "6",
          "views": "212702",
          "likes": "29282",
          "dislikes": "1108",
          "comments": "3817",
          "total_engagement": "33099",
          "engagement_rate": "0.155612",
          "trend_lag_days": "0",
          "comments_disabled": "False",
          "ratings_disabled": "False",
          "title_word_count": "8",
          "description_length": "1412",
          "description_preview": "Dimanche.\\n18h30.\\nSoyez pr\u00e9sents pour la vid\u00e9o la plus r\u00e9alistiquement haineuse du YouTube Game.\\n\\nStrike sous 24h garanti.\\n\\nMontage de NastyTanooki : https://www.youtube.com/channel/UCJvYnKvJZSIz-2deI7Xppww\\n\\n-----------------------------------------------------------------",
          "platform": "YouTube",
          "region": "France",
          "source_dataset": "youtube_trending_france",
          "record_type": "video",
          "year": "2017",
          "month": "11",
          "year_month": "2017-11",
          "year_week": "2017-W46"
        },
        {
          "video_id": "Yo84eqYwP98",
          "title": "LA PIRE PARTIE ft Le Rire Jaune, Pierre Croce, Fabien Olicard, Nad Rich' Hard, Max Bird, Studio Vrac",
          "publish_time": "2017-11-12 15:00:02",
          "trending_date": "2017-11-14",
          "channel_title": "Le Labo",
          "category_id": "24",
          "tags": "[none]",
          "primary_topic": "no_explicit_topic",
          "tag_count": "0",
          "views": "432721",
          "likes": "14053",
          "dislikes": "576",
          "comments": "1161",
          "total_engagement": "15214",
          "engagement_rate": "0.035159",
          "trend_lag_days": "1",
          "comments_disabled": "False",
          "ratings_disabled": "False",
          "title_word_count": "18",
          "description_length": "1828",
          "description_preview": "Le jeu de soci\u00e9t\u00e9: https://goo.gl/hhG1Ta\\n\\nGagner le jeu sign\u00e9 par tous les joueurs: \\n\\nCha\u00eene de Studio Vrac: https://goo.gl/HVPoJs\\nCha\u00eene du Rire Jaune: https://goo.gl/JqUGNj\\nCha\u00eene de Fabien Olicard: https://goo.gl/uc6zii\\nCha\u00eene de Nad Rich' Hard: https://goo.gl/hiy2mw\\nC",
          "platform": "YouTube",
          "region": "France",
          "source_dataset": "youtube_trending_france",
          "record_type": "video",
          "year": "2017",
          "month": "11",
          "year_month": "2017-11",
          "year_week": "2017-W46"
        },
        {
          "video_id": "ceqntSXE-10",
          "title": "DESSINS ANIME\u0301S FRANC\u0327AIS VS RUSSES 2 - Daniil le Russe",
          "publish_time": "2017-11-13 17:00:38",
          "trending_date": "2017-11-14",
          "channel_title": "Daniil le Russe",
          "category_id": "23",
          "tags": "cartoon\"|\"pok\u00e9mon\"|\"\u00e9cole\"|\"ours\"|\"\u043c\u0443\u043b\u044c\u0442\u0444\u0438\u043b\u044c\u043c",
          "primary_topic": "cartoon\"",
          "tag_count": "5",
          "views": "482153",
          "likes": "76203",
          "dislikes": "477",
          "comments": "9580",
          "total_engagement": "85783",
          "engagement_rate": "0.177917",
          "trend_lag_days": "0",
          "comments_disabled": "False",
          "ratings_disabled": "False",
          "title_word_count": "10",
          "description_length": "338",
          "description_preview": "Une nouvelle dose de dessins anim\u00e9s fran\u00e7ais et russes ! \\nLikes et dites moi quel est votre dessin anim\u00e9 pr\u00e9f\u00e9r\u00e9 en com !\\n\\nDessins anim\u00e9s russes : Ilia Mouromets (\u0418\u043b\u044c\u044f \u041c\u0443\u0440\u043e\u043c\u0435\u0446) \\nPok\u00e9mon\\nPeppa Pig\\nTcheburachka (\u0427\u0435\u0431\u0443\u0440\u0430\u0448\u043a\u0430)\\nWinnie Pooh (\u0412\u0438\u043d\u043d\u0438 \u041f\u0443\u0445) \\nFunky Cops\\nLe policier Ru",
          "platform": "YouTube",
          "region": "France",
          "source_dataset": "youtube_trending_france",
          "record_type": "video",
          "year": "2017",
          "month": "11",
          "year_month": "2017-11",
          "year_week": "2017-W46"
        }
      ]
    },
    {
      "name": "youtube_trending_japan",
      "title": "Japan YouTube Trending Videos",
      "description": "Regional YouTube trending-video behavior for Japan with views, likes, comments, and trend lag.",
      "source_file": "JPvideos.csv",
      "processed_file": "youtube_trending_japan_processed.csv",
      "notebook_file": "11_youtube_trending_japan.ipynb",
      "raw_rows": 20523,
      "processed_rows": 20523,
      "column_count": 29,
      "columns": [
        "video_id",
        "title",
        "publish_time",
        "trending_date",
        "channel_title",
        "category_id",
        "tags",
        "primary_topic",
        "tag_count",
        "views",
        "likes",
        "dislikes",
        "comments",
        "total_engagement",
        "engagement_rate",
        "trend_lag_days",
        "comments_disabled",
        "ratings_disabled",
        "title_word_count",
        "description_length",
        "description_preview",
        "platform",
        "region",
        "source_dataset",
        "record_type",
        "year",
        "month",
        "year_month",
        "year_week"
      ],
      "platforms": [
        "YouTube"
      ],
      "sentiments": [],
      "date_columns": [
        "trending_date"
      ],
      "preview": [
        {
          "video_id": "5ugKfHgsmYw",
          "title": "\u9678\u81ea\u30d8\u30ea\u3001\u5782\u76f4\u306b\u843d\u4e0b\uff1d\u8def\u4e0a\u306e\u8eca\u304c\u64ae\u5f71",
          "publish_time": "2018-02-06 03:04:37",
          "trending_date": "2018-02-07",
          "channel_title": "\u6642\u4e8b\u901a\u4fe1\u6620\u50cf\u30bb\u30f3\u30bf\u30fc",
          "category_id": "25",
          "tags": "\u4e8b\u6545|\"\u4f50\u8cc0\"|\"\u4f50\u8cc0\u770c\"|\"\u30d8\u30ea\u30b3\u30d7\u30bf\u30fc\"|\"\u30d8\u30ea\"|\"\u81ea\u885b\u968a\"|\"\u589c\u843d\"|\"\u843d\u4e0b\"|\"\u73fe\u5834\"|\"\u795e\u57fc\u5e02\"|\"\u30c9\u30e9\u30a4\u30d6\u30ec\u30b3\u30fc\u30c0\u30fc\"",
          "primary_topic": "\u4e8b\u6545",
          "tag_count": "11",
          "views": "188085",
          "likes": "591",
          "dislikes": "189",
          "comments": "0",
          "total_engagement": "591",
          "engagement_rate": "0.003142",
          "trend_lag_days": "0",
          "comments_disabled": "True",
          "ratings_disabled": "False",
          "title_word_count": "1",
          "description_length": "291",
          "description_preview": "\u4f50\u8cc0\u770c\u795e\u57fc\u5e02\u306e\u6c11\u5bb6\u306b\u589c\u843d\u3057\u305f\u9678\u4e0a\u81ea\u885b\u968a\u306e\uff21\uff28\uff16\uff14\uff24\u6226\u95d8\u30d8\u30ea\u30b3\u30d7\u30bf\u30fc\u304c\u5782\u76f4\u306b\u843d\u4e0b\u3059\u308b\u69d8\u5b50\u3092\u3001\u8fd1\u304f\u306b\u3044\u305f\u8eca\u306e\u30c9\u30e9\u30a4\u30d6\u30ec\u30b3\u30fc\u30c0\u30fc\u304c\u6349\u3048\u3066\u3044\u305f\u3053\u3068\u304c\uff16\u65e5\u5206\u304b\u3063\u305f\u3002\\n\u3000\u73fe\u5834\u306e\u5357\u304b\u3089\u64ae\u5f71\u3055\u308c\u305f\u6620\u50cf\u3067\u306f\u3001\u6771\u304b\u3089\u897f\u306b\u98db\u884c\u3059\u308b\u30d8\u30ea\u304c\u7a81\u7136\u3001\u6a5f\u9996\u3092\u4e0b\u306b\u5411\u3051\u3066\u304d\u308a\u3082\u307f\u56de\u8ee2\u3059\u308b\u3088\u3046\u306b\u843d\u4e0b\u3002\u30d8\u30ea\u306e\u6025\u964d\u4e0b\u3068\u540c\u6642\u306b\u3001\u6a5f\u4f53\u306e\u4e00\u90e8\u3068\u307f\u3089\u308c\u308b\u7269\u4f53\u304c\u843d\u3061\u3066\u3044\u304f\u69d8\u5b50\u3082\u6620\u3063\u3066\u3044\u305f\u3002\\n\u3000\u9332\u753b\u3057\u305f\u4f50\u8cc0\u57ce\u5317\u81ea\u52d5\u8eca\u5b66\u6821\uff08\u4f50\u8cc0\u5e02\uff09\u306b\u3088\u308b\u3068\u3001\u64ae\u5f71\u5834\u6240\u306f\u73fe\u5834\u304b\u3089\u7d04\uff11\uff0e\uff15\u30ad\u30ed\u30e1\u30fc\u30c8\u30eb\u5357\u306e\u795e\u57fc\u5e02\u5185\u306e\u8def\u4e0a\u3002\u6642\u9593\u8abf\u6574\u306e\u305f\u3081\u505c\u8eca\u3057\u3066\u3044\u305f\u9001\u8fce\u8eca\u306e\u30c9\u30e9\u30a4\u30d6\u30ec\u30b3\u30fc\u30c0\u30fc\u306b\u3001\u5076\u7136\u6620\u308a\u8fbc\u3093\u3067\u3044\u305f\u3068\u3044\u3046\u3002\u4f50\u8cc0\u57ce\u5317\u81ea\u52d5\u8eca\u5b66\u6821\u63d0\u4f9b\u3002\u3010",
          "platform": "YouTube",
          "region": "Japan",
          "source_dataset": "youtube_trending_japan",
          "record_type": "video",
          "year": "2018",
          "month": "2",
          "year_month": "2018-02",
          "year_week": "2018-W06"
        },
        {
          "video_id": "ohObafdd34Y",
          "title": "\u30a4\u30c3\u30c6Q \u304a\u796d\u308a\u7537\u5bae\u5ddd\u00d7\u624b\u8d8a \u5de8\u5927\u30d6\u30e9\u30f3\u30b3\u2461",
          "publish_time": "2018-02-06 04:01:56",
          "trending_date": "2018-02-07",
          "channel_title": "\u795e\u8c37\u3048\u308a\u306a Kamiya Erina 2",
          "category_id": "1",
          "tags": "[none]",
          "primary_topic": "no_explicit_topic",
          "tag_count": "0",
          "views": "90929",
          "likes": "442",
          "dislikes": "88",
          "comments": "174",
          "total_engagement": "616",
          "engagement_rate": "0.006775",
          "trend_lag_days": "0",
          "comments_disabled": "False",
          "ratings_disabled": "False",
          "title_word_count": "3",
          "description_length": "0",
          "description_preview": "",
          "platform": "YouTube",
          "region": "Japan",
          "source_dataset": "youtube_trending_japan",
          "record_type": "video",
          "year": "2018",
          "month": "2",
          "year_month": "2018-02",
          "year_week": "2018-W06"
        },
        {
          "video_id": "aBr2kKAHN6M",
          "title": "Live Views of Starman",
          "publish_time": "2018-02-06 21:38:22",
          "trending_date": "2018-02-07",
          "channel_title": "SpaceX",
          "category_id": "28",
          "tags": "[none]",
          "primary_topic": "no_explicit_topic",
          "tag_count": "0",
          "views": "6408303",
          "likes": "165892",
          "dislikes": "2331",
          "comments": "3006",
          "total_engagement": "168898",
          "engagement_rate": "0.026356",
          "trend_lag_days": "0",
          "comments_disabled": "False",
          "ratings_disabled": "False",
          "title_word_count": "4",
          "description_length": "0",
          "description_preview": "",
          "platform": "YouTube",
          "region": "Japan",
          "source_dataset": "youtube_trending_japan",
          "record_type": "video",
          "year": "2018",
          "month": "2",
          "year_month": "2018-02",
          "year_week": "2018-W06"
        }
      ]
    },
    {
      "name": "youtube_trending_south_korea",
      "title": "South Korea YouTube Trending Videos",
      "description": "Regional YouTube trending-video behavior for South Korea with views, likes, comments, and trend lag.",
      "source_file": "KRvideos.csv",
      "processed_file": "youtube_trending_south_korea_processed.csv",
      "notebook_file": "12_youtube_trending_south_korea.ipynb",
      "raw_rows": 34567,
      "processed_rows": 34567,
      "column_count": 29,
      "columns": [
        "video_id",
        "title",
        "publish_time",
        "trending_date",
        "channel_title",
        "category_id",
        "tags",
        "primary_topic",
        "tag_count",
        "views",
        "likes",
        "dislikes",
        "comments",
        "total_engagement",
        "engagement_rate",
        "trend_lag_days",
        "comments_disabled",
        "ratings_disabled",
        "title_word_count",
        "description_length",
        "description_preview",
        "platform",
        "region",
        "source_dataset",
        "record_type",
        "year",
        "month",
        "year_month",
        "year_week"
      ],
      "platforms": [
        "YouTube"
      ],
      "sentiments": [],
      "date_columns": [
        "trending_date"
      ],
      "preview": [
        {
          "video_id": "RxGQe4EeEpA",
          "title": "\uc88b\uc544 by \ubbfc\uc11c_\uc724\uc885\uc2e0_\uc88b\ub2c8 \ub2f5\uac00",
          "publish_time": "2017-11-13 07:07:36",
          "trending_date": "2017-11-14",
          "channel_title": "\ub77c\ud478\ub9c8\ucf54\ub9ac\uc544",
          "category_id": "22",
          "tags": "\ub77c\ud478\ub9c8|\"\uc724\uc885\uc2e0\"|\"\uc88b\ub2c8\"|\"\uc88b\uc544\"|\"\uc0ec\ub808\"|\"\ubbfc\uc11c\"",
          "primary_topic": "\ub77c\ud478\ub9c8",
          "tag_count": "6",
          "views": "156130",
          "likes": "1422",
          "dislikes": "40",
          "comments": "272",
          "total_engagement": "1694",
          "engagement_rate": "0.01085",
          "trend_lag_days": "0",
          "comments_disabled": "False",
          "ratings_disabled": "False",
          "title_word_count": "4",
          "description_length": "152",
          "description_preview": "\uc724\uc885\uc2e0 '\uc88b\ub2c8'\uc758 \ub2f5\uac00 '\uc88b\uc544' \ucd5c\ucd08 \uacf5\uac1c!\\n\uadf8 \uc5ec\uc790\uc758 \uc774\uc57c\uae30\ub97c \uc9c0\uae08 \ub9cc\ub098\ubcf4\uc138\uc694. \\n\\n\uc88b\uc544, \ub531 \uc78a\uae30 \uc88b\uc740 \ucd94\uc5b5 \uc815\ub3c4\uc57c\\n\ub09c \ub531 \uc54c\ub9de\uac8c \ub108\ub97c \uc0ac\ub791\ud588\uc5b4.\\n\\n'\uc88b\ub2c8'\uc758 \uadf8\uc5d0\uac8c \ubcf4\ub0b4\ub294 \uadf8 \uc5ec\uc790\uc758 \ub2f5\uac00\\n\uc560\uc808\ud55c \uc774\ubcc4 \ud6c4\uc5d0\ub3c4, \uc124\ub808\ub294 \uc0ac\ub791\uc758 \uc2dc\uc791\uc5d0\ub3c4\\n\ub77c\ud478\ub9c8\uac00 \ud568\uaed8\ud569\ub2c8\ub2e4.",
          "platform": "YouTube",
          "region": "South Korea",
          "source_dataset": "youtube_trending_south_korea",
          "record_type": "video",
          "year": "2017",
          "month": "11",
          "year_month": "2017-11",
          "year_week": "2017-W46"
        },
        {
          "video_id": "hH7wVE8OlQ0",
          "title": "JSA \uadc0\uc21c \ubd81\ud55c\uad70 \ucd1d\uaca9 \ubd80\uc0c1",
          "publish_time": "2017-11-13 10:59:16",
          "trending_date": "2017-11-14",
          "channel_title": "Edward",
          "category_id": "25",
          "tags": "JSA|\"\uadc0\uc21c\"|\"\ubd81\ud55c\uad70\"|\"\ucd1d\uaca9\"|\"\ubd80\uc0c1\"|\"JSA \uadc0\uc21c \ubd81\ud55c\uad70 \ucd1d\uaca9 \ubd80\uc0c1\"",
          "primary_topic": "jsa",
          "tag_count": "6",
          "views": "76533",
          "likes": "211",
          "dislikes": "28",
          "comments": "113",
          "total_engagement": "324",
          "engagement_rate": "0.004233",
          "trend_lag_days": "0",
          "comments_disabled": "False",
          "ratings_disabled": "False",
          "title_word_count": "5",
          "description_length": "204",
          "description_preview": "[\ucc44\ub110A\ub2e8\ub3c5]\u5317 \ubcd1\uc0ac \ud604\uc7ac '\uc758\uc2dd\ubd88\uba85'\u2026 \ud608\uc555 \ub5a8\uc5b4\uc9c0\ub294 \uc911 \\n[\ucc44\ub110A\ub2e8\ub3c5]\uc6b0\ub9ac\uce21 \ucd08\uc18c 50m \uc55e\uc11c \uc758\uc2dd \uc783\uace0 \uc4f0\ub7ec\uc838 \\n[\ucc44\ub110A\ub2e8\ub3c5]\u5317 \ubcd1\uc0ac \uadc0\uc21c \uc804 \uc774\ubbf8 \ubd81\uce21\uc11c \ucd1d\uc131 \\n[\ucc44\ub110A\ub2e8\ub3c5]\uadc0\uc21c \u5317 \ubcd1\uc0ac, \uc720\uc5d4 \ud5ec\uae30\ub85c \uc544\uc8fc\ub300\ubcd1\uc6d0 \uc774\uc1a1 \\n\u5317 \uc2e0\ubb38 \ud2b8\ub7fc\ud504\ub294 \ub299\ub2e4\ub9ac, \ud3c9\ud654 \ud30c\uad34\uc790 \ud589\uac01 \\n\ud2b8\ub7fc\ud504, \u5317 '\ub299\ub2e4\ub9ac' \ubc1c\uc5b8\uc5d0 \ubc1c\ub048 \\n\ud2b8\ub7fc\ud504 \uae40\uc815\uc740 \uc791\uace0 \ub6b1\ub6b1\u2026 \uc65c \ub098\ub97c \ubaa8\uc695\ud558\ub098",
          "platform": "YouTube",
          "region": "South Korea",
          "source_dataset": "youtube_trending_south_korea",
          "record_type": "video",
          "year": "2017",
          "month": "11",
          "year_month": "2017-11",
          "year_week": "2017-W46"
        },
        {
          "video_id": "9V8bnWUmE9U",
          "title": "\ub098\ubab0\ub77c\ud328\ubc00\ub9ac \uc6b4\ub3d9\ud654 \uc601\uc0c1 2\ud0c4 (\ube7c\ube7c\ub85c\ub370\uc774\ubc84\uc83c)",
          "publish_time": "2017-11-11 07:16:08",
          "trending_date": "2017-11-14",
          "channel_title": "\ub098\ubab0\ub77c\ud328\ubc00\ub9ac \ud56b\uc1fc",
          "category_id": "22",
          "tags": "\uc544\ub514\ub2e4\uc2a4|\"\ube7c\ube7c\ub85c\"|\"\ud56b\uc1fc\"|\"\ub098\ubab0\ub77c\ud328\ubc00\ub9ac\"|\"\ub300\ud559\ub85c\"|\"\uacf5\uc5f0\"",
          "primary_topic": "\uc544\ub514\ub2e4\uc2a4",
          "tag_count": "6",
          "views": "421409",
          "likes": "5112",
          "dislikes": "166",
          "comments": "459",
          "total_engagement": "5571",
          "engagement_rate": "0.01322",
          "trend_lag_days": "2",
          "comments_disabled": "False",
          "ratings_disabled": "False",
          "title_word_count": "5",
          "description_length": "15",
          "description_preview": "\ud37c\uac00\uc2e4\ub54c \uaf2d \ucd9c\ucc98 \ubd80\ud0c1\ub4dc\ub824\uc694",
          "platform": "YouTube",
          "region": "South Korea",
          "source_dataset": "youtube_trending_south_korea",
          "record_type": "video",
          "year": "2017",
          "month": "11",
          "year_month": "2017-11",
          "year_week": "2017-W46"
        }
      ]
    },
    {
      "name": "youtube_trending_mexico",
      "title": "Mexico YouTube Trending Videos",
      "description": "Regional YouTube trending-video behavior for Mexico with views, likes, comments, and trend lag.",
      "source_file": "MXvideos.csv",
      "processed_file": "youtube_trending_mexico_processed.csv",
      "notebook_file": "13_youtube_trending_mexico.ipynb",
      "raw_rows": 40451,
      "processed_rows": 40451,
      "column_count": 29,
      "columns": [
        "video_id",
        "title",
        "publish_time",
        "trending_date",
        "channel_title",
        "category_id",
        "tags",
        "primary_topic",
        "tag_count",
        "views",
        "likes",
        "dislikes",
        "comments",
        "total_engagement",
        "engagement_rate",
        "trend_lag_days",
        "comments_disabled",
        "ratings_disabled",
        "title_word_count",
        "description_length",
        "description_preview",
        "platform",
        "region",
        "source_dataset",
        "record_type",
        "year",
        "month",
        "year_month",
        "year_week"
      ],
      "platforms": [
        "YouTube"
      ],
      "sentiments": [],
      "date_columns": [
        "trending_date"
      ],
      "preview": [
        {
          "video_id": "SbOwzAl9ZfQ",
          "title": "Cap\u00edtulo 12 | MasterChef 2017",
          "publish_time": "2017-11-13 06:06:22",
          "trending_date": "2017-11-14",
          "channel_title": "MasterChef 2017",
          "category_id": "24",
          "tags": "MasterChef Junior 2017|\"TV Azteca\"|\"recetas\"|\"cocina\"|\"Anette Michel\"|\"Betty V\u00e1zquez\"|\"Benito Molina\"|\"Adri\u00e1n Herrera\"|\"master chef mexico\"|\"masterchef\"|\"master chef\"|\"master chef mexico 2017\"|\"masterchef mexico jueces\"|\"la cocina m\u00e1s famosa de m\u00e9xico\"|\"reality de cocina m\u00e1s famoso de m\u00e9xico\"|\"cap\u00edtulo 12\"|\"episodio 12\"|\"capitulo masterchef\"|\"capitulo masterchef mexico 2017\"|\"programa masterchef de hoy\"",
          "primary_topic": "masterchef junior 2017",
          "tag_count": "20",
          "views": "310130",
          "likes": "4182",
          "dislikes": "361",
          "comments": "1836",
          "total_engagement": "6018",
          "engagement_rate": "0.019405",
          "trend_lag_days": "0",
          "comments_disabled": "False",
          "ratings_disabled": "False",
          "title_word_count": "5",
          "description_length": "441",
          "description_preview": "Disfruta la presencia del Chef Torreblanca en MasterChef, el duelo de pasteles, las mesas regionales de los chefs Benito, Betty y Herrera, la preparaci\u00f3n de un tamal artesanal y la salida del Padre Beto.\\n\\nMasterChef 2017\\nVisita nuestro sitio oficial:\\nhttp://www.aztecatrece.co",
          "platform": "YouTube",
          "region": "Mexico",
          "source_dataset": "youtube_trending_mexico",
          "record_type": "video",
          "year": "2017",
          "month": "11",
          "year_month": "2017-11",
          "year_week": "2017-W46"
        },
        {
          "video_id": "klOV6Xh-DnI",
          "title": "ALEXA EX-INTEGRANTE DEL GRUPO TIMBIRICHE RENUNCIA A \u00a8La Voz Mexico 7\u00a8TELEVISA 11/11/2017",
          "publish_time": "2017-11-13 05:11:58",
          "trending_date": "2017-11-14",
          "channel_title": "Micky Contreras Martinez",
          "category_id": "22",
          "tags": "La Voz Mexico 7",
          "primary_topic": "la voz mexico 7",
          "tag_count": "1",
          "views": "104972",
          "likes": "271",
          "dislikes": "174",
          "comments": "369",
          "total_engagement": "640",
          "engagement_rate": "0.006097",
          "trend_lag_days": "0",
          "comments_disabled": "False",
          "ratings_disabled": "False",
          "title_word_count": "12",
          "description_length": "88",
          "description_preview": "ALEXA EX-INTEGRANTE DEL GRUPO TIMBIRICHE RENUNCIA A \u00a8La Voz Mexico 7\u00a8TELEVISA 11/11/2017",
          "platform": "YouTube",
          "region": "Mexico",
          "source_dataset": "youtube_trending_mexico",
          "record_type": "video",
          "year": "2017",
          "month": "11",
          "year_month": "2017-11",
          "year_week": "2017-W46"
        },
        {
          "video_id": "6L2ZF7Qzsbk",
          "title": "LOUIS CKAG\u00d3 - EL PULSO DE LA REP\u00daBLICA",
          "publish_time": "2017-11-13 17:00:02",
          "trending_date": "2017-11-14",
          "channel_title": "El Pulso De La Rep\u00fablica",
          "category_id": "25",
          "tags": "Chumel Torres|\"El Pulso de la Republica\"|\"noticias\"|\"news\"|\"mexico\"|\"pri\"|\"pan\"|\"prd\"|\"morena\"|\"louis ck\"|\"carstens\"|\"acoso\"|\"qatar\"|\"chicharito\"|\"premio nacional del deporte\"|\"carlos slim\"|\"carlos vergara\"|\"chivas\"|\"angelica fuentes\"",
          "primary_topic": "chumel torres",
          "tag_count": "19",
          "views": "136064",
          "likes": "10105",
          "dislikes": "266",
          "comments": "607",
          "total_engagement": "10712",
          "engagement_rate": "0.078728",
          "trend_lag_days": "0",
          "comments_disabled": "False",
          "ratings_disabled": "False",
          "title_word_count": "8",
          "description_length": "1313",
          "description_preview": "La canci\u00f3n del principio se llama \u201cEste esp\u00edritu\u201d de nuestros carnales de nuestros carnales de Corona en colaboraci\u00f3n con La Banda Bast\u00f3n y Sotomayor, esc\u00fachala completa aqu\u00ed:\\nhttps://youtu.be/pQI70NAgN-I\\nO en Spotify \\nhttps://open.spotify.com/track/1tg4Sm0RY0HMReaI0YmJuM\\n\\nE",
          "platform": "YouTube",
          "region": "Mexico",
          "source_dataset": "youtube_trending_mexico",
          "record_type": "video",
          "year": "2017",
          "month": "11",
          "year_month": "2017-11",
          "year_week": "2017-W46"
        }
      ]
    },
    {
      "name": "youtube_trending_russia",
      "title": "Russia YouTube Trending Videos",
      "description": "Regional YouTube trending-video behavior for Russia with views, likes, comments, and trend lag.",
      "source_file": "RUvideos.csv",
      "processed_file": "youtube_trending_russia_processed.csv",
      "notebook_file": "14_youtube_trending_russia.ipynb",
      "raw_rows": 40739,
      "processed_rows": 40739,
      "column_count": 29,
      "columns": [
        "video_id",
        "title",
        "publish_time",
        "trending_date",
        "channel_title",
        "category_id",
        "tags",
        "primary_topic",
        "tag_count",
        "views",
        "likes",
        "dislikes",
        "comments",
        "total_engagement",
        "engagement_rate",
        "trend_lag_days",
        "comments_disabled",
        "ratings_disabled",
        "title_word_count",
        "description_length",
        "description_preview",
        "platform",
        "region",
        "source_dataset",
        "record_type",
        "year",
        "month",
        "year_month",
        "year_week"
      ],
      "platforms": [
        "YouTube"
      ],
      "sentiments": [],
      "date_columns": [
        "trending_date"
      ],
      "preview": [
        {
          "video_id": "gDuslQ9avLc",
          "title": "\u0417\u0430\u0445\u0430\u0440 \u0438 \u041f\u043e\u043b\u0438\u043d\u0430 \u0443\u0447\u0430\u0442\u0441\u044f \u044d\u043a\u043e\u043d\u043e\u043c\u0438\u0442\u044c",
          "publish_time": "2017-11-13 09:09:31",
          "trending_date": "2017-11-14",
          "channel_title": "\u0422\u2014\u0416 \u0411\u041e\u0413\u0410\u0427",
          "category_id": "22",
          "tags": "\u0437\u0430\u0445\u0430\u0440 \u0438 \u043f\u043e\u043b\u0438\u043d\u0430|\"\u0443\u0447\u0438\u043c\u0441\u044f \u044d\u043a\u043e\u043d\u043e\u043c\u0438\u0442\u044c\"|\"\u043a\u043e\u043f\u0438\u0442\u044c \u0434\u0435\u043d\u044c\u0433\u0438\"|\"\u044d\u043a\u043e\u043d\u043e\u043c\u044c\"|\"\u043c\u0435\u043b\u043a\u0438\u0435 \u0442\u0440\u0430\u0442\u044b\"|\"\u043a\u0430\u043a \u044d\u043a\u043e\u043d\u043e\u043c\u0438\u0442\u044c \u043d\u0430 \u0435\u0434\u0435\"|\"\u0441\u043e\u0432\u0435\u0442\u044b \u044d\u043a\u043e\u043d\u043e\u043c\u0438\u0442\u044c\"|\"\u043b\u0438\u0447\u043d\u044b\u0439 \u0431\u044e\u0434\u0436\u0435\u0442\"|\"\u043f\u0440\u0438 \u043c\u0430\u043b\u0435\u043d\u044c\u043a\u043e\u0439 \u0437\u0430\u0440\u043f\u043b\u0430\u0442\u0435\"|\"\u0441\u0432\u0430\u0434\u044c\u0431\u0430\"|\"\u043f\u043e\u0434\u0433\u043e\u0442\u043e\u0432\u043a\u0430 \u043a \u0441\u0432\u0430\u0434\u044c\u0431\u0435\"|\"\u0433\u043e\u0441\u0442\u0438 \u043d\u0430 \u0441\u0432\u0430\u0434\u044c\u0431\u0435\"|\"\u043a\u0440\u0430\u0441\u0438\u0432\u0430\u044f \u0441\u0432\u0430\u0434\u044c\u0431\u0430\"|\"\u0436\u0438\u0437\u043d\u044c \u0441\u0432\u0430\u0434\u044c\u0431\u0430\"",
          "primary_topic": "\u0437\u0430\u0445\u0430\u0440 \u0438 \u043f\u043e\u043b\u0438\u043d\u0430",
          "tag_count": "14",
          "views": "62408",
          "likes": "334",
          "dislikes": "190",
          "comments": "50",
          "total_engagement": "384",
          "engagement_rate": "0.006153",
          "trend_lag_days": "0",
          "comments_disabled": "False",
          "ratings_disabled": "False",
          "title_word_count": "5",
          "description_length": "700",
          "description_preview": "\u0417\u043d\u0430\u043a\u043e\u043c\u044c\u0442\u0435\u0441\u044c, \u044d\u0442\u043e \u0417\u0430\u0445\u0430\u0440 \u0438 \u041f\u043e\u043b\u0438\u043d\u0430. \u0412\u043c\u0435\u0441\u0442\u0435 \u0441 \u043d\u0438\u043c\u0438 \u043c\u044b \u0441\u043d\u044f\u043b\u0438 \u0441\u0435\u0440\u0438\u044e \u0440\u043e\u043b\u0438\u043a\u043e\u0432 \u043e \u0441\u0435\u043c\u0435\u0439\u043d\u043e\u043c \u0431\u044e\u0434\u0436\u0435\u0442\u0435, \u044d\u043a\u043e\u043d\u043e\u043c\u0438\u0438 \u0438 \u0442\u0440\u0430\u0442\u0430\u0445. \u0412 \u043f\u0435\u0440\u0432\u043e\u043c \u0440\u043e\u043b\u0438\u043a\u0435 \u0440\u0435\u0431\u044f\u0442\u0430 \u0433\u043e\u0442\u043e\u0432\u044f\u0442\u0441\u044f \u043a \u0441\u0432\u0430\u0434\u044c\u0431\u0435 \u0438 \u0445\u043e\u0442\u044f\u0442 \u043e\u0442\u043f\u0440\u0430\u0437\u0434\u043d\u043e\u0432\u0430\u0442\u044c \u0435\u0435 \u043f\u044b\u0448\u043d\u043e. \u041d\u043e \u0431\u0435\u0437 \u043d\u0430\u043a\u043e\u043f\u043b\u0435\u043d\u0438\u0439, \u0441 \u043e\u0434\u043d\u043e\u0439 \u0437\u0430\u0440\u043f\u043b\u0430\u0442\u043e\u0439 \u043d\u0430 \u0434\u0432\u043e\u0438\u0445 \u0438 \u043a\u0443\u0447\u0435\u0439 \u043c\u0435\u043b\u043a\u0438\u0445 \u0442\u0440\u0430\u0442 \u0441\u0432\u0430\u0434\u044c\u0431\u0430 \u043c\u043e\u0436\u0435\u0442 \u043d\u0435 \u0441\u043b\u0443\u0447\u0438\u0442\u044c\u0441\u044f. \u0421\u043c",
          "platform": "YouTube",
          "region": "Russia",
          "source_dataset": "youtube_trending_russia",
          "record_type": "video",
          "year": "2017",
          "month": "11",
          "year_month": "2017-11",
          "year_week": "2017-W46"
        },
        {
          "video_id": "AOCJIFEA_jE",
          "title": "\u0411\u0438\u0440\u0436\u0430 \u041c\u0435\u043c\u043e\u0432 #29. \u0411\u043e\u043b\u044c\u0448\u043e\u0438\u0306 \u0432\u044b\u043f\u0443\u0441\u043a",
          "publish_time": "2017-11-13 17:32:11",
          "trending_date": "2017-11-14",
          "channel_title": "Druzhko Show",
          "category_id": "22",
          "tags": "\u0431\u0438\u0440\u0436\u0430 \u043c\u0435\u043c\u043e\u0432|\"\u043b\u0435\u0432 \u0448\u0430\u0433\u0438\u043d\u044f\u043d\"|\"\u043c\u0435\u043c\u044b\"|\"\u043f\u0438\u043a\u0447\u0438\"|\"\u0434\u0440\u0443\u0436\u043a\u043e\"|\"\u0434\u0440\u0443\u0436\u043a\u043e \u0448\u043e\u0443\"|\"\u0430\u043d\u043e\u043d\u0438\u043c\u0443\u0441\"|\"\u0431\u043e\u0440\u0449\"|\"ftp\"|\"\u043c\u0445\u043a\"|\"\u043d\u0430 \u0441\u043b\u0443\u0447\u0430\u0439 \u0432\u0430\u0436\u043d\u044b\u0445 \u043f\u0435\u0440\u0435\u0433\u043e\u0432\u043e\u0440\u043e\u0432\"|\"\u0430\u0444\u0444\u043b\u0435\u043a\"|\"\u0431\u044d\u043d \u0430\u0444\u0444\u043b\u0435\u043a\"|\"batman\"|\"\u0431\u044d\u0442\u043c\u0435\u043d\"|\"\u0442\u0440\u0430\u043c\u043f\"",
          "primary_topic": "\u0431\u0438\u0440\u0436\u0430 \u043c\u0435\u043c\u043e\u0432",
          "tag_count": "16",
          "views": "330043",
          "likes": "43841",
          "dislikes": "2244",
          "comments": "2977",
          "total_engagement": "46818",
          "engagement_rate": "0.141854",
          "trend_lag_days": "0",
          "comments_disabled": "False",
          "ratings_disabled": "False",
          "title_word_count": "5",
          "description_length": "834",
          "description_preview": "\u0412 29 \u0432\u044b\u043f\u0443\u0441\u043a\u0435 \u0414\u0440\u0443\u0436\u043a\u043e \u0428\u043e\u0443 \u0421\u0435\u0440\u0433\u0435\u0439 \u0441\u043a\u0430\u0437\u0430\u043b, \u0447\u0442\u043e \u0411\u0438\u0440\u0436\u0430 \u041c\u0435\u043c\u043e\u0432 \u043e\u0442\u0434\u0435\u043b\u044c\u043d\u043e \u0432\u044b\u0439\u0434\u0435\u0442 \u043d\u0430 \u0435\u0433\u043e \u043a\u0430\u043d\u0430\u043b\u0435 \u0432 \u043f\u043e\u043d\u0435\u0434\u0435\u043b\u044c\u043d\u0438\u043a\u2026\u0438 \u043d\u0435 \u0441\u043e\u0432\u0440\u0430\u043b!\\n\\n\u0412\u0441\u0442\u0440\u0435\u0447\u0430\u0439\u0442\u0435, \u0440\u0430\u0441\u0448\u0438\u0440\u0435\u043d\u043d\u0430\u044f \u0438, \u0432\u043f\u0435\u0440\u0432\u044b\u0435, \u0441\u0430\u043c\u043e\u0441\u0442\u043e\u044f\u0442\u0435\u043b\u044c\u043d\u0430\u044f \u0411\u0438\u0440\u0436\u0430 \u041c\u0435\u043c\u043e\u0432, \u0432 \u043a\u043e\u0442\u043e\u0440\u043e\u0439 \u041b\u0435\u0432 \u0432\u0441\u043f\u043e\u043c\u043d\u0438\u043b \u043b\u0443\u0447\u0448\u0438\u0435 \u043f\u0438\u043a\u0447\u0438 \u043f\u043e\u0441\u043b\u0435\u0434\u043d\u0435\u0439 \u043d\u0435\u0434\u0435\u043b\u0438, \u043e\u0431\u0441\u0443\u0434\u0438\u043b \u0441\u0430\u043c\u044b\u0435 \u043c\u0435\u043c\u043d\u044b\u0435 \u043d\u043e\u0432\u043e\u0441\u0442\u0438, \u0432\u0441\u0442\u0440\u0435\u0442\u0438\u043b\u0441\u044f \u0441 \u043e\u0447\u0435",
          "platform": "YouTube",
          "region": "Russia",
          "source_dataset": "youtube_trending_russia",
          "record_type": "video",
          "year": "2017",
          "month": "11",
          "year_month": "2017-11",
          "year_week": "2017-W46"
        },
        {
          "video_id": "VAWNQDgwwOM",
          "title": "\u0425\u0410\u0419\u041f \u041a\u042d\u041c\u041f - \u0421\u0412\u041e\u0419 \u0421\u0420\u0415\u0414\u0418 \u0427\u0423\u0416\u0418\u0425",
          "publish_time": "2017-11-13 16:11:31",
          "trending_date": "2017-11-14",
          "channel_title": "\u042e\u043b\u0438\u043a",
          "category_id": "24",
          "tags": "\u044e\u043c\u043e\u0440|\"\u043a\u043e\u043c\u0435\u0434\u0438\u044f\"|\"\u0432\u043b\u043e\u0433\"|\"\u0431\u043b\u043e\u0433\"|\"\u0441\u043c\u0435\u0448\u043d\u043e\"|\"\u0441\u043c\u0435\u0448\u043d\u043e\u0435\"|\"juliusspeak\"|\"julius speak\"|\"\u0434\u0436\u0443\u043b\u0438\u0443\u0441 \u0441\u043f\u0438\u043a\"|\"\u044e\u043b\u0438\u043a\"|\"\u0448\u0443\u0442\u043a\u0438\"|\"\u043f\u0440\u0438\u043a\u043e\u043b\u044b\"|\"\u0432\u0438\u0434\u0435\u043e\u043f\u0440\u0438\u043a\u043e\u043b\u044b\"|\"\u0445\u0430\u0439\u043f \u043a\u044d\u043c\u043f\"",
          "primary_topic": "\u044e\u043c\u043e\u0440",
          "tag_count": "14",
          "views": "424596",
          "likes": "49854",
          "dislikes": "714",
          "comments": "2944",
          "total_engagement": "52798",
          "engagement_rate": "0.124349",
          "trend_lag_days": "0",
          "comments_disabled": "False",
          "ratings_disabled": "False",
          "title_word_count": "6",
          "description_length": "257",
          "description_preview": "http://kapitany.ru/!Yulik.cap - \u0424\u0430\u043a\u0443\u043b\u044c\u0442\u0435\u0442 #\u041a\u0430\u043f\u0438\u0442\u0430\u043d\u044b\\n\u041c\u0435\u0440\u0447 - https://mamcupy.com/shop/pap-prodaj/yulik\\n\u042e\u043b\u0438\u043a - http://vk.com/oneshko\\n\u0413\u0440\u0443\u043f\u043f\u0430 - http://vk.com/juliusspeak\\n\u041b\u0430\u0439\u0432 \u043a\u0430\u043d\u0430\u043b - https://www.youtube.com/channel/UCvnVq3ay_VTc6NuwwfUzVJQ?sub_confirmation=1",
          "platform": "YouTube",
          "region": "Russia",
          "source_dataset": "youtube_trending_russia",
          "record_type": "video",
          "year": "2017",
          "month": "11",
          "year_month": "2017-11",
          "year_week": "2017-W46"
        }
      ]
    },
    {
      "name": "youtube_trending_india",
      "title": "India YouTube Trending Videos",
      "description": "Regional YouTube trending-video behavior for India with views, likes, comments, and trend lag.",
      "source_file": "INvideos.csv",
      "processed_file": "youtube_trending_india_processed.csv",
      "notebook_file": "15_youtube_trending_india.ipynb",
      "raw_rows": 37352,
      "processed_rows": 37352,
      "column_count": 29,
      "columns": [
        "video_id",
        "title",
        "publish_time",
        "trending_date",
        "channel_title",
        "category_id",
        "tags",
        "primary_topic",
        "tag_count",
        "views",
        "likes",
        "dislikes",
        "comments",
        "total_engagement",
        "engagement_rate",
        "trend_lag_days",
        "comments_disabled",
        "ratings_disabled",
        "title_word_count",
        "description_length",
        "description_preview",
        "platform",
        "region",
        "source_dataset",
        "record_type",
        "year",
        "month",
        "year_month",
        "year_week"
      ],
      "platforms": [
        "YouTube"
      ],
      "sentiments": [],
      "date_columns": [
        "trending_date"
      ],
      "preview": [
        {
          "video_id": "kzwfHumJyYc",
          "title": "Sharry Mann: Cute Munda ( Song Teaser) | Parmish Verma | Releasing on 17 November",
          "publish_time": "2017-11-12 12:20:39",
          "trending_date": "2017-11-14",
          "channel_title": "Lokdhun Punjabi",
          "category_id": "1",
          "tags": "sharry mann|\"sharry mann new song\"|\"sharry mann cute munda\"|\"sharry mann latest song\"|\"sharry mann punjabi song 2017\"|\"parmish verma\"|\"parmish verma new song\"|\"parmish verma sharry mann\"|\"parmish verma sharry mann new song\"|\"parmish verma cute munda\"|\"new punjabi song 2017\"|\"punjabi song 2017\"|\"parmish verma new song 2017\"|\"parmish verma latest song 2017\"|\"punjabi songs 2017\"",
          "primary_topic": "sharry mann",
          "tag_count": "15",
          "views": "1096327",
          "likes": "33966",
          "dislikes": "798",
          "comments": "882",
          "total_engagement": "34848",
          "engagement_rate": "0.031786",
          "trend_lag_days": "1",
          "comments_disabled": "False",
          "ratings_disabled": "False",
          "title_word_count": "15",
          "description_length": "919",
          "description_preview": "Presenting Sharry Mann latest Punjabi Song Cute Munda Teaser . The music of new punjabi song is given by Gift Rulers while lyrics are penned by Zaildar Pargat Singh. The video is directed by Parmish Verma. \\nEnjoy and stay connected with us!! \\n\\nSong : Cute Munda\\nSinger : Sharr",
          "platform": "YouTube",
          "region": "India",
          "source_dataset": "youtube_trending_india",
          "record_type": "video",
          "year": "2017",
          "month": "11",
          "year_month": "2017-11",
          "year_week": "2017-W46"
        },
        {
          "video_id": "zUZ1z7FwLc8",
          "title": "\u092a\u0940\u0930\u093f\u092f\u0921\u094d\u0938 \u0915\u0947 \u0938\u092e\u092f, \u092a\u0947\u091f \u092a\u0930 \u092a\u0924\u093f \u0915\u0930\u0924\u093e \u0910\u0938\u093e, \u0926\u0947\u0916\u0915\u0930 \u0926\u0902\u0917 \u0930\u0939 \u091c\u093e\u092f\u0947\u0902\u0917\u0947",
          "publish_time": "2017-11-13 05:43:56",
          "trending_date": "2017-11-14",
          "channel_title": "HJ NEWS",
          "category_id": "25",
          "tags": "\u092a\u0940\u0930\u093f\u092f\u0921\u094d\u0938 \u0915\u0947 \u0938\u092e\u092f|\"\u092a\u0947\u091f \u092a\u0930 \u092a\u0924\u093f \u0915\u0930\u0924\u093e \u0910\u0938\u093e\"|\"\u0926\u0947\u0916\u0915\u0930 \u0926\u0902\u0917 \u0930\u0939 \u091c\u093e\u092f\u0947\u0902\u0917\u0947\"|\"latest news\"|\"today news\"|\"news\"|\"breaking news\"|\"current news\"|\"world news\"|\"hj news updates\"|\"bollywood updates\"|\"news channel in hindi\"|\"entertainment news\"|\"merrage\"|\"love\"|\"break up\"|\"perideus time\"|\"pragenent girl\"|\"baby born\"",
          "primary_topic": "\u092a\u0940\u0930\u093f\u092f\u0921\u094d\u0938 \u0915\u0947 \u0938\u092e\u092f",
          "tag_count": "19",
          "views": "590101",
          "likes": "735",
          "dislikes": "904",
          "comments": "0",
          "total_engagement": "735",
          "engagement_rate": "0.001246",
          "trend_lag_days": "0",
          "comments_disabled": "True",
          "ratings_disabled": "False",
          "title_word_count": "12",
          "description_length": "2230",
          "description_preview": "\u092a\u0940\u0930\u093f\u092f\u0921\u094d\u0938 \u0915\u0947 \u0938\u092e\u092f, \u092a\u0947\u091f \u092a\u0930 \u092a\u0924\u093f \u0915\u0930\u0924\u093e \u0910\u0938\u093e, \u0926\u0947\u0916\u0915\u0930 \u0926\u0902\u0917 \u0930\u0939 \u091c\u093e\u092f\u0947\u0902\u0917\u0947 \\n\\nWatch this video :- https://youtu.be/zUZ1z7FwLc8\\n\\nHere is the secret of the death of PCS wife Namrata on February 16, 2017, still persisted after 9 months. In the case, the relatives of the deceased had accused the ",
          "platform": "YouTube",
          "region": "India",
          "source_dataset": "youtube_trending_india",
          "record_type": "video",
          "year": "2017",
          "month": "11",
          "year_month": "2017-11",
          "year_week": "2017-W46"
        },
        {
          "video_id": "10L1hZ9qa58",
          "title": "Stylish Star Allu Arjun @ ChaySam Wedding Reception | TFPC",
          "publish_time": "2017-11-12 15:48:08",
          "trending_date": "2017-11-14",
          "channel_title": "TFPC",
          "category_id": "24",
          "tags": "Stylish Star Allu Arjun @ ChaySam Wedding Reception|\"Stylish Star Allu Arjun\"|\"ChaySam Wedding Reception\"|\"nagachaitanya\"|\"samantha\"|\"chaysam\"|\"chay sam\"|\"naga chaitanya and samantha wedding reception\"|\"wedding reception\"|\"nagarjuna\"|\"akkineni wedding reception\"|\"tfpc\"|\"telugu cinema\"|\"celebrities @ chaysam wedding reception\"",
          "primary_topic": "stylish star allu arjun @ chaysam wedding reception",
          "tag_count": "14",
          "views": "473988",
          "likes": "2011",
          "dislikes": "243",
          "comments": "149",
          "total_engagement": "2160",
          "engagement_rate": "0.004557",
          "trend_lag_days": "1",
          "comments_disabled": "False",
          "ratings_disabled": "False",
          "title_word_count": "10",
          "description_length": "480",
          "description_preview": "Watch Stylish Star Allu Arjun @ ChaySam Wedding Reception \\n\\n\u261b For latest news https://www.tfpc.in, https://goo.gl/pQjhVq\\n\u261b Follow Us on https://twitter.com/tfpcin\\n\u261b Like Us on https://www.facebook.com/tfpcin\\n\u261b Follow us on https://instagram.com/tfpcin/\\n\\n\u25ba Latest Telugu Cin",
          "platform": "YouTube",
          "region": "India",
          "source_dataset": "youtube_trending_india",
          "record_type": "video",
          "year": "2017",
          "month": "11",
          "year_month": "2017-11",
          "year_week": "2017-W46"
        }
      ]
    },
    {
      "name": "youtube_publish_country_snapshot",
      "title": "Cross-Country YouTube Trending Snapshot",
      "description": "Compact YouTube trending snapshot with publish-country coverage, day-of-week, and time-frame metadata.",
      "source_file": "youtube.csv",
      "processed_file": "youtube_publish_country_snapshot_processed.csv",
      "notebook_file": "16_youtube_publish_country_snapshot.ipynb",
      "raw_rows": 161470,
      "processed_rows": 161470,
      "column_count": 30,
      "columns": [
        "video_id",
        "title",
        "publish_date",
        "trending_date",
        "channel_title",
        "category_id",
        "publish_country",
        "published_day_of_week",
        "time_frame",
        "tags",
        "primary_topic",
        "tag_count",
        "views",
        "likes",
        "dislikes",
        "comments",
        "total_engagement",
        "engagement_rate",
        "trend_lag_days",
        "comments_disabled",
        "ratings_disabled",
        "title_word_count",
        "platform",
        "region",
        "source_dataset",
        "record_type",
        "year",
        "month",
        "year_month",
        "year_week"
      ],
      "platforms": [
        "YouTube"
      ],
      "sentiments": [],
      "date_columns": [
        "publish_date",
        "trending_date"
      ],
      "preview": [
        {
          "video_id": "2kyS6SvSYSE",
          "title": "WE WANT TO TALK ABOUT OUR MARRIAGE",
          "publish_date": "2017-11-13",
          "trending_date": "2017-11-14",
          "channel_title": "CaseyNeistat",
          "category_id": "22",
          "publish_country": "US",
          "published_day_of_week": "Monday",
          "time_frame": "17:00 to 17:59",
          "tags": "SHANtell martin",
          "primary_topic": "shantell martin",
          "tag_count": "1",
          "views": "748374",
          "likes": "57527",
          "dislikes": "2966",
          "comments": "15954",
          "total_engagement": "73481",
          "engagement_rate": "0.098188",
          "trend_lag_days": "1",
          "comments_disabled": "False",
          "ratings_disabled": "False",
          "title_word_count": "7",
          "platform": "YouTube",
          "region": "United States",
          "source_dataset": "youtube_publish_country_snapshot",
          "record_type": "video",
          "year": "2017",
          "month": "11",
          "year_month": "2017-11",
          "year_week": "2017-W46"
        },
        {
          "video_id": "1ZAPwfrtAFY",
          "title": "The Trump Presidency: Last Week Tonight with John Oliver (HBO)",
          "publish_date": "2017-11-13",
          "trending_date": "2017-11-14",
          "channel_title": "LastWeekTonight",
          "category_id": "24",
          "publish_country": "US",
          "published_day_of_week": "Monday",
          "time_frame": "7:00 to 7:59",
          "tags": "last week tonight trump presidency|\"last week tonight donald trump\"\"|\"\"john oliver trump\"\"|\"\"donald trump\"\"\"",
          "primary_topic": "last week tonight trump presidency",
          "tag_count": "4",
          "views": "2418783",
          "likes": "97185",
          "dislikes": "6146",
          "comments": "12703",
          "total_engagement": "109888",
          "engagement_rate": "0.045431",
          "trend_lag_days": "1",
          "comments_disabled": "False",
          "ratings_disabled": "False",
          "title_word_count": "10",
          "platform": "YouTube",
          "region": "United States",
          "source_dataset": "youtube_publish_country_snapshot",
          "record_type": "video",
          "year": "2017",
          "month": "11",
          "year_month": "2017-11",
          "year_week": "2017-W46"
        },
        {
          "video_id": "5qpjK5DgCt4",
          "title": "Racist Superman | Rudy Mancuso, King Bach & Lele Pons",
          "publish_date": "2017-11-12",
          "trending_date": "2017-11-14",
          "channel_title": "Rudy Mancuso",
          "category_id": "23",
          "publish_country": "US",
          "published_day_of_week": "Sunday",
          "time_frame": "19:00 to 19:59",
          "tags": "racist superman|\"rudy\"\"|\"\"mancuso\"\"|\"\"king\"\"|\"\"bach\"\"|\"\"racist\"\"|\"\"superman\"\"|\"\"love\"\"|\"\"rudy mancuso poo bear black white official music video\"\"|\"\"iphone x by pineapple\"\"|\"\"lelepons\"\"|\"\"hannahstocking\"\"|\"\"rudymancuso\"\"|\"\"inanna\"\"|\"\"anwar\"\"|\"\"sarkis\"\"|\"\"shots\"\"|\"\"shotsstudios\"\"|\"\"alesso\"\"|\"\"anitta\"\"|\"\"brazil\"\"|\"\"Getting My Driver's License | Lele Pons\"\"\"",
          "primary_topic": "racist superman",
          "tag_count": "23",
          "views": "3191434",
          "likes": "146033",
          "dislikes": "5339",
          "comments": "8181",
          "total_engagement": "154214",
          "engagement_rate": "0.048321",
          "trend_lag_days": "2",
          "comments_disabled": "False",
          "ratings_disabled": "False",
          "title_word_count": "10",
          "platform": "YouTube",
          "region": "United States",
          "source_dataset": "youtube_publish_country_snapshot",
          "record_type": "video",
          "year": "2017",
          "month": "11",
          "year_month": "2017-11",
          "year_week": "2017-W46"
        }
      ]
    }
  ]
}